gmsh.py
gmsh-4.12.1.data/data/lib/gmsh-4.12.dll
gmsh-4.12.1.data/data/lib/gmsh.lib
gmsh-4.12.1.data/data/lib/gmsh.jl
gmsh-4.12.1.data/data/share/doc/gmsh/CHANGELOG.txt
gmsh-4.12.1.data/data/share/doc/gmsh/CREDITS.txt
gmsh-4.12.1.data/data/share/doc/gmsh/LICENSE.txt
gmsh-4.12.1.data/data/share/doc/gmsh/README.txt
gmsh-4.12.1.data/data/share/doc/gmsh/examples/api/CMakeLists.txt
gmsh-4.12.1.data/data/share/doc/gmsh/examples/api/README.txt
gmsh-4.12.1.data/data/share/doc/gmsh/examples/api/adapt_mesh.cpp
gmsh-4.12.1.data/data/share/doc/gmsh/examples/api/adapt_mesh.py
gmsh-4.12.1.data/data/share/doc/gmsh/examples/api/aneurysm.py
gmsh-4.12.1.data/data/share/doc/gmsh/examples/api/aneurysm_data.stl
gmsh-4.12.1.data/data/share/doc/gmsh/examples/api/as1-tu-203.stp
gmsh-4.12.1.data/data/share/doc/gmsh/examples/api/bgmesh.pos
gmsh-4.12.1.data/data/share/doc/gmsh/examples/api/boolean.cpp
gmsh-4.12.1.data/data/share/doc/gmsh/examples/api/boolean.py
gmsh-4.12.1.data/data/share/doc/gmsh/examples/api/bspline_bezier_patches.py
gmsh-4.12.1.data/data/share/doc/gmsh/examples/api/bspline_bezier_trimmed.py
gmsh-4.12.1.data/data/share/doc/gmsh/examples/api/bspline_filling.py
gmsh-4.12.1.data/data/share/doc/gmsh/examples/api/circle_arc.py
gmsh-4.12.1.data/data/share/doc/gmsh/examples/api/closest_point.py
gmsh-4.12.1.data/data/share/doc/gmsh/examples/api/copy_mesh.py
gmsh-4.12.1.data/data/share/doc/gmsh/examples/api/crack.py
gmsh-4.12.1.data/data/share/doc/gmsh/examples/api/crack3d.py
gmsh-4.12.1.data/data/share/doc/gmsh/examples/api/custom_gui.cpp
gmsh-4.12.1.data/data/share/doc/gmsh/examples/api/custom_gui.py
gmsh-4.12.1.data/data/share/doc/gmsh/examples/api/cylinderFFD.py
gmsh-4.12.1.data/data/share/doc/gmsh/examples/api/discrete.cpp
gmsh-4.12.1.data/data/share/doc/gmsh/examples/api/discrete.jl
gmsh-4.12.1.data/data/share/doc/gmsh/examples/api/discrete.py
gmsh-4.12.1.data/data/share/doc/gmsh/examples/api/edges.cpp
gmsh-4.12.1.data/data/share/doc/gmsh/examples/api/explore.cpp
gmsh-4.12.1.dist-info/METADATA
gmsh-4.12.1.dist-info/WHEEL
gmsh-4.12.1.dist-info/top_level.txt
/tmp/tmpgmu9jhda/gmsh-4.12.1.dist-info/RECORD
